setup.cfg
setup.py
beer/__init__.py
beer.egg-info/PKG-INFO
beer.egg-info/SOURCES.txt
beer.egg-info/dependency_links.txt
beer.egg-info/pbr.json
beer.egg-info/top_level.txt