Metadata-Version: 1.0
Name: beer
Version: 0.1.0
Summary: Wouldn't it be great thought?
Home-page: https://github.com/schae234/Beer
Author: Rob Schaefer
Author-email: schae234@gmail.com
License: Creative Commons Attribution-NonCommercial-ShareAlike 4.0 International License
Platform: UNKNOWN
